sphinx_adc_theme/__init__.py
sphinx_adc_theme/layout.html
sphinx_adc_theme/theme.conf
sphinx_adc_theme/static/css/adctheme.css
sphinx_adc_theme/static/css/mobile.css
sphinx_adc_theme/static/img/arrow-head-left.gif
sphinx_adc_theme/static/img/breadcrumb_background.png
sphinx_adc_theme/static/img/documentation.png
sphinx_adc_theme/static/img/header_sm_mid.png
sphinx_adc_theme/static/img/invisible.gif
sphinx_adc_theme/static/img/scrn1.png
sphinx_adc_theme/static/img/scrn2.png
sphinx_adc_theme/static/img/searchfield_leftcap.png
sphinx_adc_theme/static/img/searchfield_repeat.png
sphinx_adc_theme/static/img/searchfield_rightcap.png
sphinx_adc_theme/static/img/title_background.png
sphinx_adc_theme/static/img/triangle_closed.png
sphinx_adc_theme/static/img/triangle_left.png
sphinx_adc_theme/static/img/triangle_open.png
sphinx_adc_theme/static/js/toc.js
sphinx_adc_theme-0.1.7.dist-info/LICENSE
sphinx_adc_theme-0.1.7.dist-info/METADATA
sphinx_adc_theme-0.1.7.dist-info/WHEEL
sphinx_adc_theme-0.1.7.dist-info/entry_points.txt
sphinx_adc_theme-0.1.7.dist-info/top_level.txt
sphinx_adc_theme-0.1.7.dist-info/RECORD
