Metadata-Version: 2.1
Name: sphinx-adc-theme
Version: 0.1.7
Summary: Apple Developer Connection theme for Sphinx, 2015 version.
Home-page: https://github.com/mga-sphinx/sphinx_adc_theme
Author: Christophe CHAUVET
Author-email: christophe.chauvet@gmail.com
License: BSD
Project-URL: Bug Tracker, https://github.com/mga-sphinx/sphinx_adc_theme/issues
Project-URL: Documentation, https://github.com/mga-sphinx/sphinx_adc_theme/blob/master/README.rst
Project-URL: Source Code, https://github.com/mga-sphinx/sphinx_adc_theme
Project-URL: Demo, http://mga-sphinx.github.io/sphinx_adc_theme/
Keywords: sphinx theme
Platform: UNKNOWN
Classifier: Development Status :: 5 - Production/Stable
Classifier: License :: OSI Approved :: BSD License
Classifier: Environment :: Console
Classifier: Environment :: Web Environment
Classifier: Framework :: Sphinx
Classifier: Framework :: Sphinx :: Theme
Classifier: Intended Audience :: Developers
Classifier: Programming Language :: Python :: 2.7
Classifier: Programming Language :: Python :: 3
Classifier: Programming Language :: Python :: 3.5
Classifier: Programming Language :: Python :: 3.6
Classifier: Programming Language :: Python :: 3.7
Classifier: Programming Language :: Python :: 3.8
Classifier: Programming Language :: Python :: Implementation :: PyPy
Classifier: Operating System :: OS Independent
Classifier: Topic :: Documentation
Classifier: Topic :: Software Development :: Documentation
Requires-Dist: docutils (>=0.14)
